codeoceansdk/Capsule.py
codeoceansdk/CodeOcean.py
codeoceansdk/Computation.py
codeoceansdk/DataAsset.py
codeoceansdk/IO.py
codeoceansdk/Pipeline.py
codeoceansdk/__init__.py
codeoceansdk-1.0.0.dist-info/METADATA
codeoceansdk-1.0.0.dist-info/WHEEL
codeoceansdk-1.0.0.dist-info/licenses/LICENSE
codeoceansdk-1.0.0.dist-info/RECORD
