Metadata-Version: 2.1
Name: codeoceansdk
Version: 1.0.0
Summary: A set of functions to interact with the Code Ocean API
Project-URL: Homepage, https://github.com/codeocean/codeoceansdk-py
Project-URL: Bug Tracker, https://github.com/codeocean/codeoceansdk-py/issues
Author-email: June Snedecor <june@codeocean.com>
License-Expression: MIT
License-File: LICENSE
Classifier: License :: OSI Approved :: MIT License
Classifier: Operating System :: OS Independent
Classifier: Programming Language :: Python :: 3
Requires-Python: >=3.10
Requires-Dist: pandas
Requires-Dist: requests
Provides-Extra: doc
Requires-Dist: pdoc; extra == 'doc'
Provides-Extra: test
Requires-Dist: pytest; extra == 'test'
Requires-Dist: pytest-skip-slow; extra == 'test'
